lyrical/__init__.py
lyrical/lyrical.py
lyrical-1.1.3.dist-info/licenses/LICENSE
lyrical-1.1.3.dist-info/METADATA
lyrical-1.1.3.dist-info/WHEEL
lyrical-1.1.3.dist-info/top_level.txt
lyrical-1.1.3.dist-info/RECORD
