Metadata-Version: 2.4
Name: lyrical
Version: 1.1.3
Summary: Python package to fetch song lyrics from Genius
Author-email: SnarkyDev <snarkydev@outlook.com>
Maintainer-email: SnarkyDev <snarkydev@outlook.com>
License: # MIT License
Project-URL: Homepage, https://github.com/SnarkyDeveloper/Lyrical
Project-URL: Bug Reports, https://github.com/SnarkyDeveloper/Lyrical/issues
Project-URL: Source, https://github.com/SnarkyDeveloper/Lyrical
Keywords: lyrics,genius,music,songs
Classifier: Development Status :: 4 - Beta
Classifier: Intended Audience :: Developers
Classifier: Topic :: Software Development :: Libraries :: Python Modules
Classifier: Topic :: Multimedia :: Sound/Audio
Classifier: License :: OSI Approved :: MIT License
Classifier: Programming Language :: Python :: 3
Classifier: Programming Language :: Python :: 3.9
Classifier: Programming Language :: Python :: 3.10
Classifier: Programming Language :: Python :: 3.11
Classifier: Programming Language :: Python :: 3.12
Requires-Python: >=3.9
License-File: LICENSE
Requires-Dist: httpx
Requires-Dist: beautifulsoup4
Requires-Dist: fastapi
Requires-Dist: uvicorn
Dynamic: license-file
